{"cacheTime": 1595095891, "baseUrl": "https://kater.me/d/67608", "title": "什麼時候520有特別的節日ㄌ", "content": [{"author": "shitpost裡沒有F，但廢文裡有", "body": "\n<p>\n 到去年都還沒有吧\n </p>\n<p>\n 至少我沒感覺到\n </p>\n<p>\n 阿不對去年520我也在報告地獄中\n </p>\n"}, {"author": "白稿紙", "body": "\n<p>\n<a href=\"https://i.imgur.com/6ltGo7U.jpg\" rel=\"nofollow noreferrer\" target=\"_blank\">\n<img alt=\"\" src=\"https://i.imgur.com/6ltGo7U.jpg\" title=\"\"/>\n</a>\n</p>\n"}, {"author": "000", "body": "\n<p>\n 一直都有呀\n <br/>\n 就是從諧音轉變成情人節的\n <br/>\n 也不太算節日就是ㄌ\n </p>\n"}, {"author": "DOU5、希臘問號", "body": "\n<p>\n 計量日\n </p>\n"}, {"author": "可可蘿的頭號大粉絲", "body": "\n<p>\n 我不知道…\n </p>\n"}]}