{"cacheTime": 1595239127, "baseUrl": "https://kater.me/d/67648", "title": "PS4/Switch百合恐怖新作《夜點燈》的第三彈宣傳影像", "content": [{"author": "Soro", "body": "\n<p>\n 日本一公開PS4/Switch百合恐怖新作《夜點燈》的第三彈宣傳影像，展現了本作的恐怖氣氛。這款遊戲的日版將於7月30日正式發售。\n </p>\n<p>\n 這是一款發生在神樂原女子學園這所過去曾被成為大小姐學校的舞台中的恐怖文字冒險遊戲，圍繞著神樂原女子學園箏曲部的五個女成員，在這之間展開了一連串奇妙的事件…\n <br/>\n Youtube：\n <br/>\n<span data-s9e-mediaembed=\"youtube\" style=\"display:inline-block;width:100%;max-width:640px\">\n<span style=\"display:block;overflow:hidden;position:relative;padding-bottom:56.25%\">\n<iframe allowfullscreen=\"\" scrolling=\"no\" src=\"https://www.youtube.com/embed/E4NAkl9P\" style=\"background:url(https://i.ytimg.com/vi/E4NAkl9P/hqdefault.jpg) 50% 50% / cover;border:0;height:100%;left:0;position:absolute;width:100%\">\n</iframe>\n</span>\n</span>\n</p>\n<blockquote class=\"uncited\">\n<div>\n<p>\n 我愛日本一\n </p>\n</div>\n</blockquote>\n"}, {"author": "katerであるグループに審判された359番号だ", "body": "\n<p>\n 無法看 這遊戲我喜歡看人直播\n </p>\n"}, {"author": "Fruit丨vinegar", "body": "\n<p>\n 這好像不錯\n </p>\n<p>\n 我很喜歡屍體派對那種劇情舞台\n </p>\n"}]}