{"cacheTime": 1595288446, "baseUrl": "https://kater.me/d/65699", "title": "說真的 PC game是不是快被淘汰了啊？", "content": [{"author": "巴掌精", "body": "\n<p>\n 感覺一定會欸\n </p>\n<p>\n 畢竟個人電腦可能也快了\n </p>\n"}, {"author": "Soro", "body": "\n<p>\n<a class=\"PostMention\" data-id=\"714771\" href=\"https://kater.me/d/65699/1\">\n 巴掌精\n </a>\n 個人電腦=.=?\n </p>\n"}, {"author": "月下唯雪", "body": "\n<p>\n<a class=\"PostMention\" data-id=\"714771\" href=\"https://kater.me/d/65699/1\">\n 巴掌精\n </a>\n</p>\n<p>\n 放心，虛擬擴充實境裝置出來都不一定倒了\n <br/>\n 不只遊戲用\n <br/>\n 商業或軍事用需要性很高\n </p>\n"}, {"author": "frienkie", "body": "\n<p>\n<a class=\"PostMention\" data-id=\"714771\" href=\"https://kater.me/d/65699/1\">\n 巴掌精\n </a>\n 当你用着32寸4K屏幕玩游戏的感觉是完全无法替代的。\n </p>\n"}, {"author": "None", "body": "\n<p>\n 所以我以後沒辦法再玩到色色的遊戲了嗎…\n </p>\n"}, {"author": "可惡想成為大佬", "body": "\n<p>\n 什麼PCgame\n </p>\n"}, {"author": "Fruit丨vinegar", "body": "\n<p>\n 我只能說\n </p>\n<p>\n 只有電腦才能玩到色情遊戲喔\n </p>\n"}, {"author": "鉀金屬色調色盤", "body": "\n<p>\n ？？？\n </p>\n"}, {"author": "Leon", "body": "\n<p>\n 手遊都嘛炒短線撈錢居多\n </p>\n<p>\n 不就成本低高報酬 反正手遊除了音G其他一概不碰\n </p>\n"}, {"author": "海森堡", "body": "\n<p>\n 2022年就淘汰了\n </p>\n"}, {"author": "戰讚顫", "body": "\n<p>\n SAO出來\n <br/>\n 誰還跟你玩批吸給(≧▽≦)\n </p>\n"}]}