{"cacheTime": 1589604888, "baseUrl": "https://kater.me/d/65890", "title": "賞試把每天做過的夢都記下來", "content": [{"author": "小智的木木梟", "body": "\n<p>\n 記得的話…\n <br/>\n 今天是夢到跟一群陌生人到了一個很遠的海灘玩\n <br/>\n 還要自己走過去 大概像很多人在跑馬拉松\n <br/>\n 然後到了又被告知關了\n <br/>\n 然後又照原路走回去\n <br/>\n 然後我就醒了\n <br/>\n 真亂\n </p>\n"}, {"author": "別認錯在我不了打我會了", "body": "\n<p>\n 蒸棒，我幾乎都記不住自己的夢境\n </p>\n"}, {"author": "小智的木木梟", "body": "\n<p>\n<a class=\"PostMention\" data-id=\"716780\" href=\"https://kater.me/d/65890/2\">\n 別認錯在我不了打我會了\n </a>\n 有些夢的印象特別深 不知道為什麼\n </p>\n"}, {"author": "∅nu", "body": "\n<p>\n 睡到一半用鬧鐘吵醒，能更容易記得夢的細節\n </p>\n"}, {"author": "小智的木木梟", "body": "\n<p>\n<a class=\"PostMention\" data-id=\"716855\" href=\"https://kater.me/d/65890/4\">\n ∅nu\n </a>\n 難怪我都記得==\n <br/>\n 最近我媽都很會挑時間 在我睡得正爽的時候衝進來吵醒我\n </p>\n"}, {"author": "∅nu", "body": "\n<p>\n<a class=\"PostMention\" data-id=\"716857\" href=\"https://kater.me/d/65890/5\">\n 小智的木木梟\n </a>\n 這也太致鬱了\n </p>\n"}, {"author": "小智的木木梟", "body": "\n<p>\n<a class=\"PostMention\" data-id=\"716867\" href=\"https://kater.me/d/65890/6\">\n ∅nu\n </a>\n 睡到中途被吵醒真的會不爽\n </p>\n"}, {"author": "雜碎兔", "body": "\n<p>\n 幹很累…\n </p>\n"}]}