{"cacheTime": 1595090211, "baseUrl": "https://kater.me/d/68503", "title": "請問6.5mm跟6.35mm的音源線是一樣的嗎？", "content": [{"author": "⠀⠀⠀Noneed⠀⠀⠀", "body": "\n<p>\n 我知道耳機用的好像是3.5mm\n <br/>\n 要插音響的麥克風有6.5mm跟6.35mm\n <br/>\n 可是這兩種是一樣的嗎？\n <br/>\n 不然6.35mm的音響只能用6.35mm的麥克風插？\n </p>\n"}, {"author": "蔡陰魂還錢", "body": "\n<p>\n 不一樣吧\n </p>\n"}, {"author": "⠀⠀⠀Noneed⠀⠀⠀", "body": "\n<p>\n<a class=\"PostMention\" data-id=\"737573\" href=\"https://kater.me/d/68503/2\">\n 蔡陰魂還錢\n </a>\n<br/>\n 所以同一個音響不是每種有線麥克風都可以插嗎？\n </p>\n"}, {"author": "蔡陰魂還錢", "body": "\n<p>\n<a class=\"PostMention\" data-id=\"737608\" href=\"https://kater.me/d/68503/3\">\n ⠀⠀⠀Noneed⠀⠀⠀\n </a>\n 窩不知道\n </p>\n"}]}