{"cacheTime": 1595239912, "baseUrl": "https://kater.me/d/74414", "title": "廚6", "content": [{"author": "Soro", "body": "\n<p>\n 熱狗是女生==\n </p>\n"}, {"author": "青霧島響", "body": "\n<p>\n 什麼時候要結婚\n </p>\n"}, {"author": "Soro", "body": "\n<p>\n<a class=\"PostMention\" data-id=\"779663\" href=\"https://kater.me/d/74414/2\">\n 青霧島響\n </a>\n 等他有ㄐㄐ\n </p>\n"}, {"author": "棉被單", "body": "\n<p>\n 到時候我包200\n </p>\n"}, {"author": "Soro", "body": "\n<p>\n<a class=\"PostMention\" data-id=\"779665\" href=\"https://kater.me/d/74414/4\">\n 棉被單\n </a>\n 150就好\n </p>\n"}]}