{"cacheTime": 1595239129, "baseUrl": "https://kater.me/d/64706", "title": "￼  炫耀性侵男童影片 2少女下場曝光", "content": [{"author": "katerであるグループに審判された359番号だ", "body": "\n<p>\n ￼\n </p>\n<p>\n 炫耀性侵男童影片 2少女下場曝光\n </p>\n<p>\n 三立新聞網\n </p>\n<p>\n 三立新聞網 setn.com\n </p>\n<p>\n 2020年5月10日 23:00\n </p>\n<p>\n 國際中心／朱祖儀報導\n <br/>\n 男女都有可能成為性犯罪的受害者！日前挪威一名19歲少女和17歲朋友一起邀請12歲男童到家裡，沒想到才過沒多久，她們就將男童帶到臥室侵犯，甚至將過程拍成影片，並分享到網路上炫耀。事後此事曝光，學校急忙向警方報案，2名女孩才受到懲罰。\n </p>\n<p>\n 據《NRK》報導，2名女孩在2019年5月以心理輔導為由，將該名男童誘拐回家，當時還有一名15歲女孩在場，但她們並沒有理會該名女孩，就直接將男童帶進臥房發生性行為。事後她們還將3P的過程拍下，並分享給15歲女孩觀賞，以及放到網路上炫耀。之後過了2天，15歲女孩無法忍受2名少女的行為，將此事告知老師，此事才因此曝光。\n </p>\n<p>\n 雖然事後12歲男童表示，自己並不是在受到壓力、威脅或者利誘的情況下，和2名女孩發生性行為，但因為挪威法律規定，與14歲以下兒童發生性行為，均認定為性侵最，因此19歲女孩和17歲女孩仍須面對刑責，為自己的錯負起責任。\n <br/>\n 此案最初2人均被判處3年有期徒刑，但之後19歲女孩被改判2年8個月緩刑，17歲女孩則因為犯案時尚未成年，因此以青少年刑罰替代監禁，但2人均需支付給男童賠償金，約7萬5000元挪威克朗（約台幣22萬）。\n <br/>\n x 尊重身體自主權！請撥打113、110\n </p>\n<p>\n<a href=\"https://www.google.com/amp/s/tw.news.yahoo.com/amphtml/%25E7%2582%25AB%25E8%2580%2580%25E6%2580%25A7%25E4%25BE%25B5%25E7%2594%25B7%25E7%25AB%25A5%25E5%25BD%25B1%25E7%2589%2587-2%25E5%25B0%2591%25E5%25A5%25B3%25E4%25B8%258B%25E5%25A0%25B4%25E6%259B%259D%25E5%2585%2589-150022892.html\" rel=\"nofollow noreferrer\" target=\"_blank\">\n https://www.google.com/amp/s/tw.news.yahoo.com/amphtml/%25E7%2582%25AB%25E8%2580%2580%25E6%2580%25A7%25E4%25BE%25B5%25E7%2594%25B7%25E7%25AB%25A5%25E5%25BD%25B1%25E7%2589%2587-2%25E5%25B0%2591%25E5%25A5%25B3%25E4%25B8%258B%25E5%25A0%25B4%25E6%259B%259D%25E5%2585%2589-150022892.html\n </a>\n</p>\n<p>\n 羨慕 有的幹又有錢拿\n </p>\n"}, {"author": "電腦玩家傑夫", "body": "\n<p>\n 私外流\n </p>\n"}, {"author": "腐人家☆", "body": "\n<p>\n 最(x) 罪(o)\n </p>\n"}, {"author": "桃園阿澤_梗文製造™執行長", "body": "\n<p>\n<a href=\"https://i.imgur.com/7KZzJxq.jpg\" rel=\"nofollow noreferrer\" target=\"_blank\">\n<img alt=\"\" src=\"https://i.imgur.com/7KZzJxq.jpg\" title=\"\"/>\n</a>\n</p>\n"}, {"author": "吉艮吉影", "body": "\n<p>\n 放到網路上..\n </p>\n<p>\n 卡\n </p>\n"}, {"author": "llllllllll", "body": "\n<p>\n 2019年的事情= =現在報\n </p>\n"}]}