{"cacheTime": 1595092549, "baseUrl": "https://kater.me/d/64776", "title": "現在卡特有點卡", "content": [{"author": "可惡想成為大佬", "body": "\n<p>\n 很卡\n </p>\n<p>\n 度ㄉ\n </p>\n<p>\n 發個文都在那邊跑跑跑\n </p>\n"}, {"author": "shitpost裡沒有F，但廢文裡有", "body": "\n<p>\n 卡特有特嗎？\n </p>\n"}, {"author": "可惡想成為大佬", "body": "\n<p>\n<a class=\"PostMention\" data-id=\"705306\" href=\"https://kater.me/d/64776/2\">\n shitpost裡沒有F，但廢文裡有\n </a>\n<br/>\n 廣告不實！\n </p>\n<p>\n 竟然只有卡沒有特！\n </p>\n"}, {"author": "可可蘿的頭號大粉絲", "body": "\n<p>\n 很卡\n <br/>\n 很特\n </p>\n"}]}