{"cacheTime": 1595096445, "baseUrl": "https://kater.me/d/76091", "title": "我要公開那個男人的惡行", "content": [{"author": "蔡陰魂還錢", "body": "\n<p>\n<img alt=\"\" src=\"https://cdn.discordapp.com/attachments/638580127160336435/653247147965415435/FB_IMG_1575346510069.jpg\" title=\"\"/>\n<br/>\n<img alt=\"\" src=\"https://cdn.discordapp.com/attachments/638580127160336435/653247148632047629/EKx63nqUcAArN40.jpeg\" title=\"\"/>\n<br/>\n<img alt=\"\" src=\"https://cdn.discordapp.com/attachments/638580127160336435/653247148632047627/EKx63nsU4AAwR0W.jpeg\" title=\"\"/>\n<br/>\n 那個罪惡的男人在幾個月前偷偷範圍私訊好幾個人\n <br/>\n 把消夜圖放在成人節點騙人點進去\n <br/>\n 我現在要報復社會\n <br/>\n 請看\n </p>\n"}, {"author": "Leon", "body": "\n<p>\n Loko…\n </p>\n"}, {"author": "青霧島響", "body": "\n<p>\n 我看到了\n <br/>\n 謝謝你！\n </p>\n"}, {"author": "一番星", "body": "\n<p>\n 謝謝\n <br/>\n 我飽了\n </p>\n"}, {"author": "二夜子", "body": "\n<p>\n Loko…\n </p>\n"}, {"author": "棉被單", "body": "\n<p>\n 好惡\n </p>\n"}, {"author": "別再打了我不會認錯的", "body": "\n<p>\n 我幹你老師\n </p>\n"}, {"author": "柯巴伯茲", "body": "\n<p>\n 你很惡\n </p>\n"}]}