{"cacheTime": 1595276360, "baseUrl": "https://kater.me/d/66050", "title": "北上前進", "content": [{"author": "小黑犬宇嚎狺嗷", "body": "\n<p>\n 出發前進\n </p>\n"}, {"author": "None", "body": "\n<p>\n 北上讚…\n <br/>\n<iframe allow=\"autoplay *\" allowfullscreen=\"\" data-s9e-mediaembed=\"twitter\" onload=\"var c=new MessageChannel;c.port1.onmessage=function(e){style.height=e.data+'px'};contentWindow.postMessage('s9e:init','https://s9e.github.io',[c.port2])\" scrolling=\"no\" src=\"https://s9e.github.io/iframe/2/twitter.min.html#1010132761410093057\" style=\"background:url(https://abs.twimg.com/favicons/favicon.ico) no-repeat 50% 50%;border:0;height:250px;max-width:500px;width:100%\">\n</iframe>\n</p>\n"}, {"author": "可可蘿的頭號大粉絲", "body": "\n<p>\n<a class=\"PostMention\" data-id=\"718090\" href=\"https://kater.me/d/66050/2\">\n None\n </a>\n<br/>\n 硬\n <br/>\n 很想讓她大破\n </p>\n"}, {"author": "Fruit丨vinegar", "body": "\n<p>\n<a class=\"PostMention\" data-id=\"718090\" href=\"https://kater.me/d/66050/2\">\n None\n </a>\n</p>\n<p>\n 超級北上大人\n </p>\n"}]}