{"cacheTime": 1595260103, "baseUrl": "https://kater.me/d/66160", "title": "-gate", "content": [{"author": "可以但是殘廢", "body": "\n<p>\n combining form\n <br/>\n suffix: -gate\n <br/>\n in nouns denoting an actual or alleged scandal, especially one involving a cover-up.\n </p>\n<p>\n Etymology\n <br/>\n early 1970s: suggested by the Watergate scandal in the US, 1972.\n </p>\n<p>\n 看時事，學英語\n <br/>\n<a href=\"https://www.google.com/search?q=%22-GATE%22+mean&amp;oq=%22-GATE%22+mean&amp;aqs=chrome..69i57j0l7.11952j0j7&amp;sourceid=chrome&amp;ie=UTF-8\" rel=\"nofollow noreferrer\" target=\"_blank\">\n ref\n </a>\n</p>\n"}, {"author": "全都不認識-邊緣到真的全都不認識", "body": "\n<p>\n 蛤\n </p>\n"}, {"author": "可以但是殘廢", "body": "\n<p>\n<a class=\"PostMention\" data-id=\"719350\" href=\"https://kater.me/d/66160/2\">\n 全都不認識-邊緣到真的全都不認識\n </a>\n obamagate\n </p>\n"}]}