{"cacheTime": 1595101756, "baseUrl": "https://kater.me/d/63015", "title": "喝完水感覺好多了", "content": [{"author": "一番星", "body": "\n<p>\n 想吐和頭暈的感覺消失了\n <br/>\n 這天氣一定要多補充水分= =\n </p>\n"}, {"author": "別再打了我不會認錯的", "body": "\n<p>\n 不用啦\n </p>\n"}, {"author": "一番星", "body": "\n<p>\n<a class=\"PostMention\" data-id=\"691866\" href=\"https://kater.me/d/63015/2\">\n 別再打了我不會認錯的\n </a>\n 要啦\n </p>\n<p>\n<a class=\"PostMention\" data-id=\"691867\" href=\"https://kater.me/d/63015/3\">\n 蔡陰魂還錢\n </a>\n 請喝 請\n </p>\n"}, {"author": "蔡陰魂還錢", "body": "\n<p>\n 請多飲哦\n </p>\n"}]}