{"cacheTime": 1594566925, "baseUrl": "https://kater.me/d/82069", "title": "好扯喔，google帳號被盜", "content": [{"author": "䴑鵅䲪鴌襾", "body": "\n<p>\n 密碼全英文還可以被登，我看是谷歌賣得吧\n <br/>\n 最慘的是7/1號登入的，完全沒有注意到\n </p>\n"}, {"author": "sir流v", "body": "\n<p>\n<a class=\"PostMention\" data-id=\"835068\" href=\"https://kater.me/d/82069/1\">\n 䴑鵅䲪鴌襾\n </a>\n<br/>\n gmail可以看登入IP\n <br/>\n 然後\n <br/>\n 截圖到臨近的派出所報案\n <br/>\n 最後要記得改密碼\n <br/>\n 電腦要記得掃毒\n </p>\n"}, {"author": "Leon", "body": "\n<p>\n 窩怎都沒事\n </p>\n"}, {"author": "䴑鵅䲪鴌襾", "body": "\n<p>\n<a class=\"PostMention\" data-id=\"835069\" href=\"https://kater.me/d/82069/2\">\n Leon\n </a>\n 大概是因為我常載一些不好說的東西吧\n </p>\n"}, {"author": "青霧島響", "body": "\n<p>\n \\|/\n </p>\n"}, {"author": "徒手劈南瓜", "body": "\n<p>\n 跌落隙縫呀\n </p>\n"}, {"author": "䴑鵅䲪鴌襾", "body": "\n<p>\n<a class=\"PostMention\" data-id=\"835073\" href=\"https://kater.me/d/82069/4\">\n 徒手劈南瓜\n </a>\n<br/>\n 你是誰\n </p>\n"}, {"author": "徒手劈南瓜", "body": "\n<p>\n<a class=\"PostMention\" data-id=\"835074\" href=\"https://kater.me/d/82069/5\">\n 䴑鵅䲪鴌襾\n </a>\n 我要如何在你不知道誰是誰的狀態下告訴你我是誰？\n </p>\n"}, {"author": "䴑鵅䲪鴌襾", "body": "\n<p>\n<a class=\"PostMention\" data-id=\"835075\" href=\"https://kater.me/d/82069/6\">\n 徒手劈南瓜\n </a>\n<br/>\n 你怎麼看出暱稱的\n </p>\n"}, {"author": "徒手劈南瓜", "body": "\n<p>\n<a class=\"PostMention\" data-id=\"835077\" href=\"https://kater.me/d/82069/8\">\n 䴑鵅䲪鴌襾\n </a>\n 亂猜的\n </p>\n"}, {"author": "DOU5、希臘問號", "body": "\n<p>\n 完蛋了\n <br/>\n 你要被完全掌握了\n </p>\n"}, {"author": "䴑鵅䲪鴌襾", "body": "\n<p>\n<a class=\"PostMention\" data-id=\"835081\" href=\"https://kater.me/d/82069/10\">\n DOU5、希臘問號\n </a>\n<br/>\n 幸好沒有重要東西在裡頭\n <br/>\n 註冊的臉書也只是個動漫頭貼假帳號而已\n </p>\n"}, {"author": "Z", "body": "\n<p>\n 這裡可以看是哪裡流出來的\n </p>\n<p>\n<a href=\"https://monitor.firefox.com/\" rel=\"nofollow noreferrer\" target=\"_blank\">\n https://monitor.firefox.com/\n </a>\n</p>\n"}, {"author": "䴑鵅䲪鴌襾", "body": "\n<p>\n<a class=\"PostMention\" data-id=\"835104\" href=\"https://kater.me/d/82069/12\">\n Z\n </a>\n 此信箱出現於 0 場已知的資料外洩事件中。\n <br/>\n ＝ ＝\n </p>\n"}, {"author": "腐人家☆", "body": "\n<p>\n<a class=\"PostMention\" data-id=\"835104\" href=\"https://kater.me/d/82069/12\">\n Z\n </a>\n 人家拿人家自己的電子郵件試了一下，很久之前有外洩過不過人家之後有換過密碼（因為原本的密碼被人家忘記了😝）。\n </p>\n"}, {"author": "二夜子", "body": "\n<p>\n 開一下2階段認證\n </p>\n"}, {"author": "䴑鵅䲪鴌襾", "body": "\n<p>\n<a class=\"PostMention\" data-id=\"835106\" href=\"https://kater.me/d/82069/14\">\n 二夜子\n </a>\n 你是說手機號碼嗎？\n </p>\n"}, {"author": "二夜子", "body": "\n<p>\n<a class=\"PostMention\" data-id=\"835108\" href=\"https://kater.me/d/82069/15\">\n 䴑鵅䲪鴌襾\n </a>\n 綁手機這樣\n </p>\n"}, {"author": "可可蘿的頭號大粉絲", "body": "\n<p>\n 怕\n </p>\n"}, {"author": "Fruit丨vinegar", "body": "\n<p>\n 綁二次驗證\n </p>\n"}, {"author": "Fruit丨vinegar", "body": "\n<p>\n<a class=\"PostMention\" data-id=\"835310\" href=\"https://kater.me/d/82069/19\">\n sir流v\n </a>\n</p>\n<p>\n 除非是國內ip 不然報案沒什麼用\n </p>\n"}, {"author": "䴑鵅䲪鴌襾", "body": "\n<p>\n<a class=\"PostMention\" data-id=\"835310\" href=\"https://kater.me/d/82069/19\">\n sir流v\n </a>\n<br/>\n<iframe allowfullscreen=\"\" data-s9e-mediaembed=\"imgur\" onload=\"var c=new MessageChannel;c.port1.onmessage=function(e){var d=e.data.split(' ');style.height=d[0]+'px';style.width=d[1]+'px'};contentWindow.postMessage('s9e:init','https://s9e.github.io',[c.port2])\" scrolling=\"no\" src=\"https://s9e.github.io/iframe/2/imgur.min.html#sEBhj4H\" style=\"border:0;height:400px;max-width:100%;width:542px\">\n</iframe>\n</p>\n<p>\n 修但幾類\n <br/>\n 這個網站騙我\n </p>\n"}]}