{"cacheTime": 1595103361, "baseUrl": "https://kater.me/d/82278", "title": "為甚麼我熊貓網沒法辦註冊", "content": [{"author": "可撥肥宅", "body": "\n<p>\n 明明都有填好啊，一直停在註冊的畫面，沒辦法跳轉去登錄界面，有人能幫我嗎？\n </p>\n"}, {"author": "蘿莉好夥伴", "body": "\n<p>\n<a class=\"PostMention\" data-id=\"836571\" href=\"https://kater.me/d/82278/1\">\n 可撥肥宅\n </a>\n 因為亞洲ip無法登錄\n </p>\n"}, {"author": "可撥肥宅", "body": "\n<p>\n<a class=\"PostMention\" data-id=\"836580\" href=\"https://kater.me/d/82278/2\">\n 蘿莉好夥伴\n </a>\n 我有用vpn喔，不會這麼白癡拉\n </p>\n"}, {"author": "jerry1234", "body": "\n<p>\n<a class=\"UserMention\" href=\"https://kater.me/u/龍龍探險尋祕寶-拉風英勇奪你心\">\n @龍龍探險尋祕寶-拉風英勇奪你心\n </a>\n</p>\n"}, {"author": "龍龍探險尋祕寶-拉風英勇奪你心", "body": "\n<p>\n = =\n </p>\n"}, {"author": "sir流v", "body": "\n<p>\n ～不過我有註冊成功🤔\n </p>\n"}, {"author": "Fruit丨vinegar", "body": "\n<p>\n<a class=\"PostMention\" data-id=\"837647\" href=\"https://kater.me/d/82278/7\">\n 可撥肥宅\n </a>\n</p>\n<p>\n 記得清cookie\n </p>\n"}, {"author": "sir流v", "body": "\n<p>\n 我記得沒用vpn也能註冊啊🤔\n </p>\n"}, {"author": "龍龍探險尋祕寶-拉風英勇奪你心", "body": "\n<p>\n<a class=\"PostMention\" data-id=\"837655\" href=\"https://kater.me/d/82278/8\">\n sir流v\n </a>\n 2014後亞洲IP都被檔無法直接辦exhentai帳戶，或者說可以辦，但你進不去\n <br/>\n ehentai仍正常可進\n </p>\n"}, {"author": "可撥肥宅", "body": "\n<p>\n<a class=\"PostMention\" data-id=\"837897\" href=\"https://kater.me/d/82278/9\">\n Fruit丨vinegar\n </a>\n 有清，我整個紀錄都清了\n </p>\n"}, {"author": "我是沙織姊姊♥", "body": "\n<p>\n 我註冊兩年了，都還是登不進去🤔\n </p>\n"}, {"author": "蘿莉好夥伴", "body": "\n<p>\n<a class=\"PostMention\" data-id=\"838190\" href=\"https://kater.me/d/82278/11\">\n 我是沙織姊姊♥\n </a>\n<br/>\n 版務好像不能用熊貓\n </p>\n"}]}