{"cacheTime": 1594805617, "baseUrl": "https://kater.me/d/83564", "title": "有貓咪", "content": [{"author": "小黑犬宇嚎狺嗷", "body": "\n<p>\n 但我是犬派的，休想我會摸你\n </p>\n"}, {"author": "腐人家☆", "body": "\n<p>\n 人家是貓派的但還是很喜歡摸狗狗啊！\n </p>\n"}, {"author": "shitpost裡沒有F，但廢文裡有", "body": "\n<p>\n 不行\n </p>\n<p>\n 我對貓毛過敏\n </p>\n"}, {"author": "沒一個好的，駁回", "body": "\n<p>\n 請摸他\n </p>\n"}, {"author": "Soro", "body": "\n<p>\n<a class=\"PostMention\" data-id=\"844877\" href=\"https://kater.me/d/83564/4\">\n 沒一個好的，駁回\n </a>\n 我摸你\n </p>\n"}, {"author": "沒一個好的，駁回", "body": "\n<p>\n<a class=\"PostMention\" data-id=\"844902\" href=\"https://kater.me/d/83564/5\">\n Soro\n </a>\n 好色喔\n </p>\n"}]}