{"cacheTime": 1595486590, "baseUrl": "https://kater.me/d/64105", "title": "這樣裝消毒水", "content": [{"author": "F是那個噁F噁起來的F", "body": "\n<p>\n<a href=\"https://i.imgur.com/HPMksdq.jpg\" rel=\"nofollow noreferrer\" target=\"_blank\">\n<img alt=\"\" src=\"https://i.imgur.com/HPMksdqh.jpg\" title=\"\"/>\n</a>\n</p>\n<p>\n 會不會被誤食啊？\n </p>\n"}, {"author": "katerであるグループに審判された359番号だ", "body": "\n<p>\n<a class=\"PostMention\" data-id=\"700486\" href=\"https://kater.me/d/64105/1\">\n F是那個噁F噁起來的F\n </a>\n 我會當飲料\n </p>\n"}, {"author": "雞雞雞", "body": "\n<p>\n 想喝\n </p>\n"}, {"author": "None", "body": "\n<p>\n 讓窩想到這ㄍ\n <br/>\n<iframe allow=\"autoplay *\" allowfullscreen=\"\" data-s9e-mediaembed=\"twitter\" onload=\"var c=new MessageChannel;c.port1.onmessage=function(e){style.height=e.data+'px'};contentWindow.postMessage('s9e:init','https://s9e.github.io',[c.port2])\" scrolling=\"no\" src=\"https://s9e.github.io/iframe/2/twitter.min.html#1246406941020053507\" style=\"background:url(https://abs.twimg.com/favicons/favicon.ico) no-repeat 50% 50%;border:0;height:250px;max-width:500px;width:100%\">\n</iframe>\n</p>\n"}, {"author": "棉被單", "body": "\n<p>\n 看起來很會解渴\n </p>\n"}, {"author": "青霧島響", "body": "\n<p>\n 之前有看到\n <br/>\n 還以為是看錯\n </p>\n"}, {"author": "桃園阿澤", "body": "\n<p>\n 之前防疫記者會\n <br/>\n 中時記者就當場開蓋喝\n </p>\n<p>\n 不愧是有經過專業元素週期表攝取訓練\n </p>\n"}]}