{"cacheTime": 1589907222, "baseUrl": "https://kater.me/d/67008", "title": "青霧…", "content": [{"author": "雜碎兔", "body": "\n<p>\n 我看到了…\n <br/>\n 克萊因真的好慘😢\n </p>\n"}, {"author": "TrashFixed", "body": "\n<p>\n 靠北，原來他明子排序不是青島喔==\n </p>\n"}, {"author": "雜碎兔", "body": "\n<p>\n<a class=\"PostMention\" data-id=\"726221\" href=\"https://kater.me/d/67008/2\">\n TrashFixed\n </a>\n あおじま…\n </p>\n"}, {"author": "躺在程式裡悠閒的一枚希臘問號", "body": "\n<p>\n 他怎麼了\n <br/>\n 被當經驗包友切切死了嗎？\n </p>\n"}, {"author": "雜碎兔", "body": "\n<p>\n<a class=\"PostMention\" data-id=\"726225\" href=\"https://kater.me/d/67008/3\">\n 躺在程式裡悠閒的一枚希臘問號\n </a>\n 不是\n <br/>\n 他比我高9等來扁我\n <br/>\n 結果還打不過\n </p>\n"}, {"author": "青霧島響", "body": "\n<p>\n 沒關係的！\n </p>\n"}, {"author": "6873828489677968697765756982", "body": "\n<p>\n<a class=\"PostMention\" data-id=\"726239\" href=\"https://kater.me/d/67008/6\">\n 青霧島響\n </a>\n 後面的驚嘆號讓我感覺你在逞強\n </p>\n"}, {"author": "雜碎兔", "body": "\n<p>\n<a class=\"PostMention\" data-id=\"726239\" href=\"https://kater.me/d/67008/6\">\n 青霧島響\n </a>\n 這就是愛嗎？！\n </p>\n"}, {"author": "躺在程式裡悠閒的一枚希臘問號", "body": "\n<p>\n<a class=\"PostMention\" data-id=\"726239\" href=\"https://kater.me/d/67008/6\">\n 青霧島響\n </a>\n<br/>\n 嗚嗚嗚\n <br/>\n 好感動ㄛ\n </p>\n"}, {"author": "青霧島響", "body": "\n<p>\n<a class=\"PostMention\" data-id=\"726244\" href=\"https://kater.me/d/67008/8\">\n 雜碎兔\n </a>\n 沒錯！總有一天我要用克萊因通關\n </p>\n"}, {"author": "青霧島響", "body": "\n<p>\n<a class=\"UserMention\" href=\"https://kater.me/u/6873828489677968697765756982\">\n @6873828489677968697765756982\n </a>\n 982#726243\n <br/>\n 並沒有\n <br/>\n 要越挫越勇\n </p>\n"}, {"author": "6873828489677968697765756982", "body": "\n<p>\n<a class=\"PostMention\" data-id=\"726251\" href=\"https://kater.me/d/67008/10\">\n 青霧島響\n </a>\n 你是到幾等啊… 看你都在挑戰團長了，怕啦\n </p>\n"}, {"author": "青霧島響", "body": "\n<p>\n<a class=\"PostMention\" data-id=\"726265\" href=\"https://kater.me/d/67008/12\">\n 6873828489677968697765756982\n </a>\n 51\n </p>\n"}, {"author": "6873828489677968697765756982", "body": "\n<p>\n<a class=\"PostMention\" data-id=\"726277\" href=\"https://kater.me/d/67008/13\">\n 青霧島響\n </a>\n \\|/\n </p>\n"}, {"author": "雜碎兔", "body": "\n<p>\n<a class=\"PostMention\" data-id=\"726280\" href=\"https://kater.me/d/67008/14\">\n 6873828489677968697765756982\n </a>\n 他沒死啦\n <br/>\n 現在上層都滿和平的\n </p>\n"}, {"author": "青霧島響", "body": "\n<p>\n<a class=\"PostMention\" data-id=\"726280\" href=\"https://kater.me/d/67008/14\">\n 6873828489677968697765756982\n </a>\n 還沒 勿上香\n </p>\n"}, {"author": "6873828489677968697765756982", "body": "\n<p>\n<a class=\"PostMention\" data-id=\"726284\" href=\"https://kater.me/d/67008/15\">\n 雜碎兔\n </a>\n 靠腰，我以為這串是告別式\n </p>\n"}]}