{"cacheTime": 1593004111, "baseUrl": "https://kater.me/d/68307", "title": "原來可以戰這麼久啊", "content": [{"author": "遵從團長的遺志而停不下來的ハスキー", "body": "\n<p>\n<a href=\"https://mykirito.com/report/5ec9018d659df9000a846a2c\" rel=\"nofollow noreferrer\" target=\"_blank\">\n https://mykirito.com/report/5ec9018d659df9000a846a2c\n </a>\n</p>\n"}, {"author": "青霧島響", "body": "\n<p>\n 原來隆隆石這麼強….\n </p>\n"}, {"author": "💖🧡💛💙💚💜我i你_ＭＡＮＯ教主💜💚💙💛🧡💖", "body": "\n<p>\n 狂星爆耶\n </p>\n"}, {"author": "Lv1／人類／初心者", "body": "\n<p>\n 「34次星爆是甚麼鬼啦。」\n </p>\n"}, {"author": "恐龍化身DIO", "body": "\n<p>\n 連月月都玩了\n </p>\n"}, {"author": "腺嘌呤", "body": "\n<p>\n 我玩石頭打小拳石 他對我星爆了好幾次我也是活得好好的\n </p>\n"}]}