{"cacheTime": 1595091190, "baseUrl": "https://kater.me/d/71486", "title": "30公分專用大奶", "content": [{"author": "桃園阿澤_梗文製造™執行長", "body": "\n<p>\n<a href=\"https://i.imgur.com/Sk5onnN.png\" rel=\"nofollow noreferrer\" target=\"_blank\">\n<img alt=\"\" src=\"https://i.imgur.com/Sk5onnNh.png\" title=\"\"/>\n</a>\n</p>\n"}, {"author": "佩可我婆", "body": "\n<p>\n 就沒人理他一下嗎？\n </p>\n"}, {"author": "粉君", "body": "\n<p>\n<a href=\"https://i.imgur.com/ULS34PZ.jpg\" rel=\"nofollow noreferrer\" target=\"_blank\">\n<img alt=\"\" src=\"https://i.imgur.com/ULS34PZ.jpg\" title=\"\"/>\n</a>\n</p>\n"}, {"author": "Leon", "body": "\n<p>\n<a class=\"PostMention\" data-id=\"760891\" href=\"https://kater.me/d/71486/3\">\n 粉君\n </a>\n 阿彌陀佛 老衲去了\n </p>\n"}, {"author": "青霧島響", "body": "\n<p>\n<a class=\"PostMention\" data-id=\"760891\" href=\"https://kater.me/d/71486/3\">\n 粉君\n </a>\n 謝謝你 謝謝 謝謝\n </p>\n"}, {"author": "粉君", "body": "\n<p>\n<a class=\"PostMention\" data-id=\"760894\" href=\"https://kater.me/d/71486/4\">\n Leon\n </a>\n 這我媽媽，勿意淫\n </p>\n"}, {"author": "Leon", "body": "\n<p>\n<a class=\"PostMention\" data-id=\"760900\" href=\"https://kater.me/d/71486/6\">\n 粉君\n </a>\n 老衲只是想敲木魚而已 別誤會\n </p>\n"}]}