{"cacheTime": 1595243198, "baseUrl": "https://kater.me/d/71788", "title": "〈午休時的偷情〉", "content": [{"author": "단목명연", "body": "\n<p>\n 那天原本的班導因為有事而請假了，麻煩一位我們班級都很熟悉的代課老師，我們與他關係良好，相處得很不錯，趁著這個機會，或許我們才能做一些平時班導在做不了的壞事。\n </p>\n<p>\n 當時我最要好的友人，我們那時的友誼也早已提升到了不可描述的樣子？我想這樣不足以說明我與他的關係，他是一名轉學生，沒記錯的話是從某個近海沙洲離島過來的，他從何而來其實我記不太起，自從他轉學到我當時讀的學校，我們的關係慢慢熱絡了起來，有他在身旁好像已經是生活中不可或缺的一部份，逐漸轉向奇怪的關係發展。\n </p>\n<p>\n 午休時間，我坐在他旁邊，正對面緊鄰著導師座位，就如同平常一樣，不知不覺又開始摸了起來，他總是不讓我碰他，所以我基本上都是被玩弄的那個，我們表面上是趴著的，前方的代課老師看不見我們暗下都幹著些甚麼，一開始他稍微試探了我一下，不見我反抗，隔著長褲往我的下體搓揉，或者故意去彈他，我們努力不發生太大的聲響以讓周邊的同學起疑，畢竟午休時氛圍靜悄悄的，任何雜亂的噪音都可能引人注意。\n </p>\n<p>\n 這樣做是不夠的，他更進一步把手伸進我的褲子內，隔著內褲上下搓弄，由於座位在最前排，就算不出聲音，若有同學不睡覺的，視線往我們兩個一瞥，還是能看到我們在幹嘛，我漸漸感到刺激，他也許和我分享著同樣的感受，把手伸入內褲裏套弄，先是徐緩著握住上下著動，接著加速手的律動，動作已經很大了，旁邊坐著個女同學，平常跟我們關係不錯，頭稍微往我們的方向轉，不是在睡覺的樣子，或許他有看到吧？不過我不想管這麼多，真的太舒服了，我無法忍受這樣的感官刺激，再稍微加速，再給我一點時間，射得褲子都是並不是不可能，似乎他感受到了我身體略許抽動，準備要給我更大的刺激時──\n </p>\n<p>\n 熟悉的鐘聲傳來，他恐怕瞬間恢復了理智，也把手收了回去，事後我們雙方也沒說甚麼，這件事就這麼終了了。\n </p>\n<p>\n 後來我跟那位女同學間發生了甚麼事呢，就是另一個故事了。\n </p>\n"}, {"author": "棉被單", "body": "\n<p>\n 好刺激喔\n <br/>\n 後面是女同學拍起來威脅你跟她ii\n <br/>\n 不然就散播出去的故事嗎\n </p>\n"}, {"author": "단목명연", "body": "\n<p>\n<a class=\"PostMention\" data-id=\"762271\" href=\"https://kater.me/d/71788/2\">\n 棉被單\n </a>\n 沒有啦，跟女同學的不是甚麼大事，嘻嘻威脅愛愛跟散播甚麼的\n </p>\n"}, {"author": "佩可我婆", "body": "\n<p>\n 好羨慕喔\n </p>\n"}, {"author": "단목명연", "body": "\n<p>\n<a class=\"PostMention\" data-id=\"762275\" href=\"https://kater.me/d/71788/4\">\n 佩可我婆\n </a>\n ？？\n </p>\n"}, {"author": "山豬醬", "body": "\n<p>\n 好色喔\n </p>\n"}, {"author": "단목명연", "body": "\n<p>\n<a class=\"PostMention\" data-id=\"762293\" href=\"https://kater.me/d/71788/6\">\n 山豬醬\n </a>\n 有ㄇ\n </p>\n"}, {"author": "Fruit丨vinegar", "body": "\n<p>\n 私\n </p>\n"}, {"author": "단목명연", "body": "\n<p>\n<a class=\"PostMention\" data-id=\"762314\" href=\"https://kater.me/d/71788/8\">\n Fruit丨vinegar\n </a>\n 私甚麼\n </p>\n"}, {"author": "Fruit丨vinegar", "body": "\n<p>\n<a class=\"PostMention\" data-id=\"762316\" href=\"https://kater.me/d/71788/9\">\n 단목명연\n </a>\n</p>\n<p>\n 詳細內容\n </p>\n"}, {"author": "단목명연", "body": "\n<p>\n<a class=\"PostMention\" data-id=\"762335\" href=\"https://kater.me/d/71788/10\">\n Fruit丨vinegar\n </a>\n<a href=\"https://i.imgur.com/Hi4JlJv.png\" rel=\"nofollow noreferrer\" target=\"_blank\">\n<img alt=\"\" src=\"https://i.imgur.com/Hi4JlJv.png\" title=\"\"/>\n</a>\n</p>\n"}, {"author": "단목명연", "body": "\n<p>\n 稍微補一點，這種直來直上的關係是從某天晚上被他上了之後開始的，或許在他決定上我之前，雙方就已經有點淫蕩的情愫流動著\n </p>\n"}, {"author": "放假🧨", "body": "\n<p>\n 這些機會\n </p>\n"}, {"author": "단목명연", "body": "\n<p>\n<a class=\"PostMention\" data-id=\"763342\" href=\"https://kater.me/d/71788/14\">\n 放假🧨\n </a>\n 都是屬於你的\n </p>\n"}]}