{"cacheTime": 1595093078, "baseUrl": "https://kater.me/d/72957", "title": "我必須坦承一件事", "content": [{"author": "青霧島響", "body": "\n<p>\n 當我想要挖特定一個人的很多篇文的時候\n <br/>\n 我會順便挖其他人的文\n <br/>\n 目的是看起來比較平均\n <br/>\n 不會這麼色\n </p>\n<p>\n 還有當我想要考古某個人的文章\n <br/>\n 但覺得時間還沒到的時候\n <br/>\n 會先挖其他的文章過過乾癮\n </p>\n"}, {"author": "電腦玩家傑夫", "body": "\n<p>\n<a class=\"PostMention\" data-id=\"770430\" href=\"https://kater.me/d/72957/1\">\n 青霧島響\n </a>\n 好色哦\n </p>\n"}, {"author": "佩可我婆", "body": "\n<p>\n 好色喔\n </p>\n"}, {"author": "青霧島響", "body": "\n<p>\n<a class=\"PostMention\" data-id=\"770433\" href=\"https://kater.me/d/72957/3\">\n 別再打了我不會認錯的\n </a>\n<br/>\n 我也覺得 所以我盡量克制\n </p>\n<p>\n<a class=\"PostMention\" data-id=\"770432\" href=\"https://kater.me/d/72957/2\">\n 佩可我婆\n </a>\n<br/>\n 我很色\n </p>\n"}, {"author": "別再打了我不會認錯的", "body": "\n<p>\n 感覺好變態喔\n </p>\n"}, {"author": "白稿紙", "body": "\n<p>\n 等到None的文被考古我第一個想到的絕對是你\n </p>\n"}, {"author": "青霧島響", "body": "\n<p>\n<a class=\"PostMention\" data-id=\"770435\" href=\"https://kater.me/d/72957/4\">\n 白稿紙\n </a>\n<br/>\n 不行 我不 慢慢考好了\n <br/>\n 很怕被當成變態\n </p>\n"}, {"author": "None", "body": "\n<p>\n 好色喔…\n </p>\n"}, {"author": "青霧島響", "body": "\n<p>\n<a class=\"PostMention\" data-id=\"770438\" href=\"https://kater.me/d/72957/6\">\n None\n </a>\n<br/>\n 真的很色 想考但是時機未到的時候 我會先按讚\n <br/>\n 按到的時候你就知道「唉呀這個人好色哦」\n <br/>\n<s>\n 不對我在講什麼\n </s>\n</p>\n"}, {"author": "摩霜葉玥", "body": "\n<p>\n 聽起來很專業\n </p>\n"}, {"author": "青霧島響", "body": "\n<p>\n<a class=\"PostMention\" data-id=\"770440\" href=\"https://kater.me/d/72957/7\">\n 摩霜葉玥\n </a>\n<br/>\n 不專業 很色\n </p>\n"}, {"author": "別再打了我不會認錯的", "body": "\n<p>\n<a class=\"PostMention\" data-id=\"770443\" href=\"https://kater.me/d/72957/8\">\n 青霧島響\n </a>\n</p>\n<p>\n 不用擔心\n </p>\n<p>\n 就算很變態也沒關係\n </p>\n"}, {"author": "青霧島響", "body": "\n<p>\n<a class=\"PostMention\" data-id=\"770447\" href=\"https://kater.me/d/72957/9\">\n 別再打了我不會認錯的\n </a>\n<br/>\n 不行 合法變態是要先經過允許的\n </p>\n"}, {"author": "500 Internal Server Error", "body": "\n<p>\n<a class=\"PostMention\" data-id=\"770452\" href=\"https://kater.me/d/72957/10\">\n 青霧島響\n </a>\n 可惡，把讚踩通知關掉就無法體驗到「哎呀這個人好色噢」了\n </p>\n"}, {"author": "🐲🐱‍🚀🦃🎃🥙🌮🥐🥟我不是_ＭＡＮＯ教主🐲🐱‍🚀🦃🎃🥙🌮🥐🥟", "body": "\n<p>\n 職業考古\n </p>\n"}, {"author": "青霧島響", "body": "\n<p>\n<a class=\"PostMention\" data-id=\"770548\" href=\"https://kater.me/d/72957/13\">\n 🐲🐱‍🚀🦃🎃🥙🌮🥐🥟我不是_ＭＡＮＯ教主🐲🐱‍🚀🦃🎃🥙🌮🥐🥟\n </a>\n<br/>\n 好色考古\n </p>\n<p>\n<a class=\"PostMention\" data-id=\"770553\" href=\"https://kater.me/d/72957/14\">\n 500 Internal Server Error\n </a>\n<br/>\n 太瓜張了\n </p>\n"}, {"author": "500 Internal Server Error", "body": "\n<p>\n 城門失火，殃及池魚\n </p>\n"}, {"author": "青霧島響", "body": "\n<p>\n<a class=\"PostMention\" data-id=\"770568\" href=\"https://kater.me/d/72957/16\">\n 500 Internal Server Error\n </a>\n<br/>\n 沒關係…\n <s>\n 沒有一天是不色的…\n </s>\n</p>\n"}, {"author": "500 Internal Server Error", "body": "\n<p>\n<a class=\"PostMention\" data-id=\"770576\" href=\"https://kater.me/d/72957/17\">\n 青霧島響\n </a>\n 那種色是獨有的，跟客觀事實不一樣\n </p>\n"}, {"author": "青霧島響", "body": "\n<p>\n<a class=\"PostMention\" data-id=\"770588\" href=\"https://kater.me/d/72957/18\">\n 500 Internal Server Error\n </a>\n<br/>\n 在考完之前真的每天都想挖…\n </p>\n"}, {"author": "小黑犬宇嚎狺嗷", "body": "\n<p>\n 好色哦嗷嗷\n </p>\n"}, {"author": "青霧島響", "body": "\n<p>\n<a class=\"PostMention\" data-id=\"770597\" href=\"https://kater.me/d/72957/19\">\n 小黑犬宇嚎狺嗷\n </a>\n<br/>\n 很色…\n </p>\n"}, {"author": "None", "body": "\n<p>\n 關掉讚踩通知就會變成\n <br/>\n 有人想對你做色色的事但你毫不知情\n </p>\n"}, {"author": "青霧島響", "body": "\n<p>\n<a class=\"PostMention\" data-id=\"770601\" href=\"https://kater.me/d/72957/20\">\n None\n </a>\n<br/>\n 太色了…趁人之危..\n </p>\n"}]}