{"cacheTime": 1595093001, "baseUrl": "https://kater.me/d/74014", "title": "大學生賓果", "content": [{"author": "Soro", "body": "\n<p>\n<a href=\"https://i.imgur.com/w1idc3B.jpg\" rel=\"nofollow noreferrer\" target=\"_blank\">\n<img alt=\"\" src=\"https://i.imgur.com/w1idc3B.jpg\" title=\"\"/>\n</a>\n<br/>\n<a href=\"https://i.imgur.com/XvLUPEQ.jpg\" rel=\"nofollow noreferrer\" target=\"_blank\">\n<img alt=\"\" src=\"https://i.imgur.com/XvLUPEQh.jpg\" title=\"\"/>\n</a>\n<br/>\n 其實普普通通\n </p>\n<p>\n 白單\n <br/>\n<a href=\"https://i.imgur.com/RSmtsvr.jpg\" rel=\"nofollow noreferrer\" target=\"_blank\">\n<img alt=\"\" src=\"https://i.imgur.com/RSmtsvrh.jpg\" title=\"\"/>\n</a>\n<br/>\n<a href=\"https://i.imgur.com/h9ZbwLD.jpg\" rel=\"nofollow noreferrer\" target=\"_blank\">\n<img alt=\"\" src=\"https://i.imgur.com/h9ZbwLD.jpg\" title=\"\"/>\n</a>\n</p>\n<p>\n 這是科系用賓果\n <br/>\n 你們是什麼科系，要玩可以幫你找找看\n <br/>\n<a href=\"https://i.imgur.com/pb3W6zo.jpg\" rel=\"nofollow noreferrer\" target=\"_blank\">\n<img alt=\"\" src=\"https://i.imgur.com/pb3W6zo.jpg\" title=\"\"/>\n</a>\n</p>\n"}, {"author": "DOU5、希臘問號", "body": "\n<p>\n<a href=\"https://i.imgur.com/DAeDWvf.jpg\" rel=\"nofollow noreferrer\" target=\"_blank\">\n<img alt=\"\" src=\"https://i.imgur.com/DAeDWvf.jpg\" title=\"\"/>\n</a>\n</p>\n"}, {"author": "可可蘿的頭號大粉絲", "body": "\n<p>\n<a class=\"PostMention\" data-id=\"777371\" href=\"https://kater.me/d/74014/2\">\n DOU5、希臘問號\n </a>\n<br/>\n 笑死\n </p>\n"}, {"author": "500 Internal Server Error", "body": "\n<p>\n<img alt=\"\" src=\"https://i.imgur.com/BhsE5JR.jpg\" title=\"\" width=\"300\"/>\n<img alt=\"\" src=\"https://i.imgur.com/SpIWIaR.jpg%29%5D%28https://i.imgur.com/SpIWIaR.jpg\" title=\"\" width=\"300\"/>\n</p>\n<p>\n 哇我居然有一條線ㄌ\n <br/>\n 不知道有沒有資工系版本？\n </p>\n"}, {"author": "Soro", "body": "\n<p>\n<a class=\"PostMention\" data-id=\"777373\" href=\"https://kater.me/d/74014/3\">\n 500 Internal Server Error\n </a>\n<a href=\"https://i.imgur.com/QGWVkRC.jpg\" rel=\"nofollow noreferrer\" target=\"_blank\">\n<img alt=\"\" src=\"https://i.imgur.com/QGWVkRC.jpg\" title=\"\"/>\n</a>\n</p>\n"}, {"author": "韓信點兵多益金證", "body": "\n<p>\n<a href=\"https://i.imgur.com/dvop8ig.png\" rel=\"nofollow noreferrer\" target=\"_blank\">\n<img alt=\"\" src=\"https://i.imgur.com/dvop8ig.png\" title=\"\"/>\n</a>\n</p>\n<p>\n 我贏ㄌ\n </p>\n"}, {"author": "Soro", "body": "\n<p>\n<a class=\"PostMention\" data-id=\"777376\" href=\"https://kater.me/d/74014/4\">\n 韓信點兵多益金證\n </a>\n<a href=\"https://i.imgur.com/Y2vtPiz.jpg\" rel=\"nofollow noreferrer\" target=\"_blank\">\n<img alt=\"\" src=\"https://i.imgur.com/Y2vtPiz.jpg\" title=\"\"/>\n</a>\n<br/>\n 送你\n </p>\n"}, {"author": "500 Internal Server Error", "body": "\n<p>\n<a class=\"PostMention\" data-id=\"777380\" href=\"https://kater.me/d/74014/5\">\n Soro\n </a>\n 太誇張了吧，怎麽這麼多賓果\n </p>\n<p>\n<a href=\"https://i.imgur.com/DhP9ehS.jpg\" rel=\"nofollow noreferrer\" target=\"_blank\">\n<img alt=\"\" src=\"https://i.imgur.com/DhP9ehS.jpg\" title=\"\" width=\"300\"/>\n</a>\n</p>\n<p>\n 忘記說，剛剛看到 Bingo[5][5] 真的笑爛，這樣也能玩\n </p>\n"}, {"author": "韓信點兵多益金證", "body": "\n<p>\n<a class=\"PostMention\" data-id=\"777381\" href=\"https://kater.me/d/74014/6\">\n Soro\n </a>\n 政經跟經濟不一樣&gt;:{\n </p>\n<p>\n 而且這是哪來的學店寫的= =\n </p>\n"}, {"author": "青霧島響", "body": "\n<p>\n 有沒有中庸大學生的啊\n <br/>\n 怎麼除了很認真,潮潮之外就是很廢的\n </p>\n<p>\n<a href=\"https://i.imgur.com/TsgQ6kb.png\" rel=\"nofollow noreferrer\" target=\"_blank\">\n<img alt=\"\" src=\"https://i.imgur.com/TsgQ6kb.png\" title=\"\"/>\n</a>\n<br/>\n<a href=\"https://i.imgur.com/px7ezfj.png\" rel=\"nofollow noreferrer\" target=\"_blank\">\n<img alt=\"\" src=\"https://i.imgur.com/px7ezfj.png\" title=\"\"/>\n</a>\n<br/>\n 科系的\n <br/>\n 感覺題目出的不好 程度都混在一起了\n </p>\n<p>\n<a href=\"https://i.imgur.com/yDRtNX2.png\" rel=\"nofollow noreferrer\" target=\"_blank\">\n<img alt=\"\" src=\"https://i.imgur.com/yDRtNX2.png\" title=\"\"/>\n</a>\n<br/>\n<a href=\"https://i.imgur.com/5yj0p0v.png\" rel=\"nofollow noreferrer\" target=\"_blank\">\n<img alt=\"\" src=\"https://i.imgur.com/5yj0p0v.png\" title=\"\"/>\n</a>\n</p>\n"}, {"author": "shitpost裡沒有F，但廢文裡有", "body": "\n<p>\n 沒有顯著啊！！！！！！！！\n </p>\n<p>\n<a href=\"https://i.imgur.com/zoWzQSR.png\" rel=\"nofollow noreferrer\" target=\"_blank\">\n<img alt=\"\" src=\"https://i.imgur.com/zoWzQSR.png\" title=\"\"/>\n</a>\n</p>\n"}, {"author": "Soro", "body": "\n<p>\n<a class=\"PostMention\" data-id=\"777432\" href=\"https://kater.me/d/74014/10\">\n 韓信點兵多益金證\n </a>\n 真假 我以為是一樣欸=.=\n <br/>\n 我太笨ㄌ\n <br/>\n 這次應該找對\n <br/>\n<a href=\"https://i.imgur.com/7ELTjzT.jpg\" rel=\"nofollow noreferrer\" target=\"_blank\">\n<img alt=\"\" src=\"https://i.imgur.com/7ELTjzT.jpg\" title=\"\"/>\n</a>\n</p>\n"}, {"author": "妳沒說我怎麼知道啦", "body": "\n<p>\n<a href=\"https://i.imgur.com/6SRW5ur.jpg\" rel=\"nofollow noreferrer\" target=\"_blank\">\n<img alt=\"\" src=\"https://i.imgur.com/6SRW5ur.jpg\" title=\"\"/>\n</a>\n<br/>\n 連不起來…\n <br/>\n 資本主義的確是個無法阻止的海嘯\n </p>\n"}, {"author": "幼稚低年齡層的卡特人359號", "body": "\n<p>\n 只要卡這串就可以知道你們什麼系了\n </p>\n"}, {"author": "可可蘿的頭號大粉絲", "body": "\n<p>\n 卡位開電腦弄\n </p>\n<p>\n<a href=\"https://i.imgur.com/o0kwAic.jpg\" rel=\"nofollow noreferrer\" target=\"_blank\">\n<img alt=\"\" src=\"https://i.imgur.com/o0kwAich.jpg\" title=\"\"/>\n</a>\n</p>\n<p>\n<a href=\"https://i.imgur.com/mWEKvvX.jpg\" rel=\"nofollow noreferrer\" target=\"_blank\">\n<img alt=\"\" src=\"https://i.imgur.com/mWEKvvX.jpg\" title=\"\"/>\n</a>\n</p>\n"}, {"author": "可可蘿的頭號大粉絲", "body": "\n<p>\n<a class=\"PostMention\" data-id=\"777799\" href=\"https://kater.me/d/74014/15\">\n 可可蘿的頭號大粉絲\n </a>\n<br/>\n 這個蠻好玩的 但就是舊了點\n </p>\n<p>\n 有一些可以特別講一下的梗\n <br/>\n 從左上開始\n </p>\n<p>\n 1.被問到什麼系的時候不太想說\n <br/>\n 這個應該大家都一樣\n <br/>\n 不過是怕被問法律問題\n <br/>\n 又不會回答的時候\n </p>\n<p>\n 2.同1.問過好幾次了\n </p>\n<p>\n 3.會背民法184條\n <br/>\n 因為這條叫做「侵權行為」一個很基本的東西就對了\n </p>\n<p>\n 4.數學很爛…\n <br/>\n 那邊格子不夠畫不進去\n <br/>\n 但是算遺產難是在分配，不是在數學計算上\n </p>\n<p>\n 5.政治人物\n <br/>\n 總統\n </p>\n<p>\n 6.補習班的書比較有用\n <br/>\n 這裡我吐槽一下，教科書才是根本的內容，教科書不讀熟去讀補習班的你也看不懂\n <br/>\n 所以…嗯\n </p>\n<p>\n 7.被告誡過不能當恐龍法官\n <br/>\n 我刑法老師開學對我們說的第一句話是\n <br/>\n 「嗨各位恐龍蛋們」\n </p>\n<p>\n 8.法律追訴權大笑\n <br/>\n 沒那麼誇張，只是用語上的以訛傳訛，不會隨便笑人…\n <br/>\n 正確來說是「保留法律上任何權利」\n </p>\n<p>\n 9.判決書讀懂國文變差\n <br/>\n 是真的，因為又曲折又一堆古字，普通的文章反而看不懂\n </p>\n<p>\n 10.人家在放暑假你在準備國考\n <br/>\n 我大學後的每個暑假都沒玩到\n </p>\n<p>\n 11.律師法官以外出路\n <br/>\n 有蠻多的，但普通人對司法體系比較直觀就是法官檢察官律師\n </p>\n<p>\n 12.修法會大哭\n <br/>\n 對，因為要整個重學\n </p>\n<p>\n 13.雙重否定\n <br/>\n 這個最好笑，因為常常在老判決裡面都是這種說法，法官為了表示謙虛他們會繞圈子說話\n <br/>\n 比如說：\n <br/>\n 我覺得用這個條文是錯的→尚不得以此刑責相繩\n <br/>\n 有理由→尚難謂非無理由\n <br/>\n 這樣是合法的→尚非法所不許\n </p>\n<p>\n 14.留英美留德衝突\n <br/>\n 其實他遺漏了日派也是衝突點，不過德派依然是主流\n <br/>\n 畢竟我們的法律也幾乎都是抄德國的\n </p>\n<p>\n 15.不需要背法條\n <br/>\n 常用就會記起來，本來就不用特別背\n </p>\n<p>\n 16.寫考卷常常會用「管見以為」、「退萬步言」\n <br/>\n 其實跟13.類似\n <br/>\n 只是換成考生自謙的詞而已，類似的還有「愚見以為」、「學生以為」，但我都用「本文以為」\n <br/>\n 因為字最少啊。\n </p>\n<p>\n 17.釋字617號就嘆氣\n <br/>\n 其實是在講猥褻物品的定義還有散布問題，處理的不好就是了\n </p>\n<p>\n 18.定型化契約會看完\n <br/>\n 對，誰知道他藏什麼在裡面\n </p>\n<p>\n 19.聊天爆出法律用語\n <br/>\n 大部分都是開玩笑的，對不熟的人講我覺得很白癡\n </p>\n<p>\n 19.天龍八部\n <br/>\n 來源是非常有名的民法教授「王澤鑑」教授所寫的「民法學說與判例研究(一)～(八)」\n <br/>\n 因為太經典，考生必看\n </p>\n<p>\n 20.蘇案、盧正案跟李師科案\n <br/>\n 其實我只知道蘇案\n </p>\n"}, {"author": "別再打了我不會認錯的", "body": "\n<p>\n<a href=\"https://i.imgur.com/WWkT7EO.png\" rel=\"nofollow noreferrer\" target=\"_blank\">\n<img alt=\"\" src=\"https://i.imgur.com/WWkT7EO.png\" title=\"\"/>\n</a>\n</p>\n<p>\n 新細明體\n </p>\n"}]}