{"cacheTime": 1595095427, "baseUrl": "https://kater.me/d/75428", "title": "哈哈爽啦，支票畫平行線真的考了", "content": [{"author": "可可蘿的頭號大粉絲", "body": "\n<p>\n 舒服\n <br/>\n 猜題王\n </p>\n"}, {"author": "500 Internal Server Error", "body": "\n<p>\n 這是替我們死老百姓增加知識的善報！\n </p>\n"}, {"author": "可可蘿的頭號大粉絲", "body": "\n<p>\n<a class=\"PostMention\" data-id=\"785872\" href=\"https://kater.me/d/75428/2\">\n 500 Internal Server Error\n </a>\n<br/>\n 票據法第139條\n <br/>\n 請參閱\n <br/>\n 請\n </p>\n<p>\n 沒\n <br/>\n 簡單來說就是在支票上畫兩道平行線\n <br/>\n 代表付款人只能對金融機構付款\n </p>\n<p>\n 防止有支票拿去銀行兌現的有心人\n </p>\n"}, {"author": "Fruit丨vinegar", "body": "\n<p>\n 希望我也有開支票的一天\n </p>\n"}, {"author": "可可蘿的頭號大粉絲", "body": "\n<p>\n<a class=\"PostMention\" data-id=\"785991\" href=\"https://kater.me/d/75428/4\">\n Fruit丨vinegar\n </a>\n<br/>\n 只要500元以上就能開\n </p>\n<p>\n<a class=\"PostMention\" data-id=\"786002\" href=\"https://kater.me/d/75428/5\">\n 別再打了我不會認錯的\n </a>\n<br/>\n 一個很趣的東西\n <br/>\n 很趣\n </p>\n"}, {"author": "別再打了我不會認錯的", "body": "\n<p>\n 啥\n </p>\n"}]}