{"cacheTime": 1595354078, "baseUrl": "https://kater.me/d/78178", "title": "廢文仔= =", "content": [{"author": "為什麼不拜拜", "body": "\n<p>\n (¯―¯٥)\n </p>\n"}, {"author": "青霧島響", "body": "\n<p>\n Σ(´∀｀；)\n </p>\n"}, {"author": "有咲有推", "body": "\n<p>\n<a href=\"https://i.imgur.com/pHDuo7g.png\" rel=\"nofollow noreferrer\" target=\"_blank\">\n<img alt=\"\" src=\"https://i.imgur.com/pHDuo7g.png\" title=\"\"/>\n</a>\n</p>\n"}, {"author": "旅行者", "body": "\n<p>\n<a href=\"https://i.imgur.com/U57GGoK.gif\" rel=\"nofollow noreferrer\" target=\"_blank\">\n<img alt=\"\" src=\"https://i.imgur.com/U57GGoK.gif\" title=\"\"/>\n</a>\n</p>\n"}]}