{"cacheTime": 1595243334, "baseUrl": "https://kater.me/d/80585", "title": "如果台灣的輕小說或是小說都弄成這個大小", "content": [{"author": "Soro", "body": "\n<p>\n 更方便隨時隨地看了\n <br/>\n<a href=\"https://i.imgur.com/LCrf6LH.jpg\" rel=\"nofollow noreferrer\" target=\"_blank\">\n<img alt=\"\" src=\"https://i.imgur.com/LCrf6LHh.jpg\" title=\"\"/>\n</a>\n</p>\n"}, {"author": "可可蘿的頭號大粉絲", "body": "\n<p>\n 文本\n </p>\n"}, {"author": "Soro", "body": "\n<p>\n<a class=\"PostMention\" data-id=\"825027\" href=\"https://kater.me/d/80585/2\">\n 可可蘿的頭號大粉絲\n </a>\n 4啊 通常這小本的就是一堆鬼故事或是總裁系列才會出小本的…\n </p>\n"}, {"author": "有咲有推", "body": "\n<p>\n 你手也太大了吧\n </p>\n"}, {"author": "Soro", "body": "\n<p>\n<a class=\"PostMention\" data-id=\"825038\" href=\"https://kater.me/d/80585/4\">\n 有咲有推\n </a>\n 是書太小…\n </p>\n"}, {"author": "sir流v", "body": "\n<p>\n 好奇底下那本的書名🤔\n </p>\n"}, {"author": "Soro", "body": "\n<p>\n<a class=\"PostMention\" data-id=\"825048\" href=\"https://kater.me/d/80585/5\">\n sir流v\n </a>\n<a href=\"https://i.imgur.com/PuPOpNu.jpg\" rel=\"nofollow noreferrer\" target=\"_blank\">\n<img alt=\"\" src=\"https://i.imgur.com/PuPOpNuh.jpg\" title=\"\"/>\n</a>\n</p>\n"}]}