{"cacheTime": 1595103447, "baseUrl": "https://kater.me/d/83852", "title": "有些羨慕，能跟同事聊星爆的人", "content": [{"author": "𝓓𝓾𝓜𝓮𝓲𝔁𝓲𝓷", "body": "\n<p>\n 我的環境，不允許==\n </p>\n"}, {"author": "可可蘿的頭號大粉絲", "body": "\n<p>\n 擺出那個姿勢\n <br/>\n 就會引來獨行玩家了\n </p>\n"}, {"author": "𝓓𝓾𝓜𝓮𝓲𝔁𝓲𝓷", "body": "\n<p>\n<a class=\"PostMention\" data-id=\"846737\" href=\"https://kater.me/d/83852/2\">\n 可可蘿的頭號大粉絲\n </a>\n</p>\n<p>\n<a class=\"PostMention\" data-id=\"846739\" href=\"https://kater.me/d/83852/3\">\n 電腦玩家傑夫\n </a>\n</p>\n<p>\n<a class=\"PostMention\" data-id=\"846752\" href=\"https://kater.me/d/83852/4\">\n 蔡陰魂還錢\n </a>\n</p>\n<p>\n 不過，倒是真的喊過幫我撐十秒==\n </p>\n"}, {"author": "桃園阿澤_梗文製造™執行長", "body": "\n<p>\n<a class=\"PostMention\" data-id=\"846737\" href=\"https://kater.me/d/83852/2\">\n 可可蘿的頭號大粉絲\n </a>\n<br/>\n 不會\n <br/>\n 只會引來8+9\n <br/>\n<a href=\"https://i.imgur.com/l5YQ0TQ.jpg\" rel=\"nofollow noreferrer\" target=\"_blank\">\n<img alt=\"\" src=\"https://i.imgur.com/l5YQ0TQ.jpg\" title=\"\"/>\n</a>\n</p>\n"}, {"author": "電腦玩家傑夫", "body": "\n<p>\n 可能你要更快一點吧\n </p>\n"}, {"author": "蔡陰魂還錢", "body": "\n<p>\n 這就是MMO的不合理之處\n </p>\n"}, {"author": "可可蘿的頭號大粉絲", "body": "\n<p>\n<a class=\"PostMention\" data-id=\"846753\" href=\"https://kater.me/d/83852/5\">\n 𝓓𝓾𝓜𝓮𝓲𝔁𝓲𝓷\n </a>\n<br/>\n 笑死\n </p>\n"}, {"author": "𝓓𝓾𝓜𝓮𝓲𝔁𝓲𝓷", "body": "\n<p>\n<a class=\"PostMention\" data-id=\"846754\" href=\"https://kater.me/d/83852/6\">\n 可可蘿的頭號大粉絲\n </a>\n</p>\n<p>\n 那明明是很緊急的狀況==\n </p>\n"}, {"author": "可可蘿的頭號大粉絲", "body": "\n<p>\n<a class=\"PostMention\" data-id=\"846756\" href=\"https://kater.me/d/83852/7\">\n 𝓓𝓾𝓜𝓮𝓲𝔁𝓲𝓷\n </a>\n<br/>\n 74層的緊急狀況\n </p>\n"}, {"author": "឴᠌᠌឴᠌᠌឴᠌᠌឴᠌᠌឴᠌᠌឴᠌᠌", "body": "\n<p>\n 999 幫撐10秒\n </p>\n"}]}