{"cacheTime": 1588484351, "baseUrl": "https://kater.me/d/61945", "title": "哇靠她是怎麼知道的", "content": [{"author": "可可蘿的頭號大粉絲", "body": "\n<p>\n<a href=\"https://i.imgur.com/JdJI9kJ.jpg\" rel=\"nofollow noreferrer\" target=\"_blank\">\n<img alt=\"\" src=\"https://i.imgur.com/JdJI9kJ.jpg\" title=\"\"/>\n</a>\n</p>\n"}, {"author": "恐龍化身DIO", "body": "\n<p>\n<a class=\"PostMention\" data-id=\"683736\" href=\"https://kater.me/d/61945/1\">\n 可可蘿的頭號大粉絲\n </a>\n 她猜你只喜歡她的肉體\n </p>\n"}, {"author": "摩霜葉玥", "body": "\n<p>\n 你也是 就喜歡我大腿而已\n </p>\n"}, {"author": "夏卡多Shaucado", "body": "\n<p>\n<a class=\"PostMention\" data-id=\"683738\" href=\"https://kater.me/d/61945/2\">\n 摩霜葉玥\n </a>\n 私\n </p>\n"}, {"author": "可可蘿的頭號大粉絲", "body": "\n<p>\n<a class=\"PostMention\" data-id=\"683738\" href=\"https://kater.me/d/61945/2\">\n 摩霜葉玥\n </a>\n<br/>\n 私\n </p>\n"}, {"author": "Fruit丨vinegar", "body": "\n<p>\n 我也喜歡大腿\n </p>\n<p>\n 有穿褲襪更讚\n </p>\n"}, {"author": "摩霜葉玥", "body": "\n<p>\n<a class=\"PostMention\" data-id=\"683743\" href=\"https://kater.me/d/61945/4\">\n 夏卡多Shaucado\n </a>\n<br/>\n<a class=\"PostMention\" data-id=\"683769\" href=\"https://kater.me/d/61945/8\">\n 可可蘿的頭號大粉絲\n </a>\n<br/>\n 沒什麼好私的\n </p>\n"}, {"author": "我的樹呢", "body": "\n<p>\n 因為每次客人都狂摸狂舔\n <br/>\n 他當然知道自己市場在哪裡\n </p>\n"}, {"author": "雞雞雞", "body": "\n<p>\n 感覺有在賣.jpg\n </p>\n"}, {"author": "TrashFixed", "body": "\n<p>\n 如果不只呢\n </p>\n"}, {"author": "TrashFixed", "body": "\n<p>\n 如果不只呢\n </p>\n"}, {"author": "新北阿澤_職業飆車司機", "body": "\n<p>\n 其實我比較喜歡保養她的大腿\n </p>\n"}, {"author": "✨💖💖✨💕ＭＡＮＯ💕✨💖💖✨", "body": "\n<p>\n 其實全身我都愛\n </p>\n"}, {"author": "青霧島響", "body": "\n<p>\n 我要全身舔啊舔\n </p>\n"}, {"author": "佩可我婆", "body": "\n<p>\n<a href=\"https://i.imgur.com/A1zUCdK.png\" rel=\"nofollow noreferrer\" target=\"_blank\">\n<img alt=\"\" src=\"https://i.imgur.com/A1zUCdK.png\" title=\"\"/>\n</a>\n<br/>\n<a href=\"https://i.imgur.com/ttG2K6V.jpg\" rel=\"nofollow noreferrer\" target=\"_blank\">\n<img alt=\"\" src=\"https://i.imgur.com/ttG2K6Vh.jpg\" title=\"\"/>\n</a>\n</p>\n"}, {"author": "可可蘿的頭號大粉絲", "body": "\n<p>\n 香噴噴\n </p>\n"}]}